job_orchestra/__init__.py
job_orchestra/pipeline.py
job_orchestra/py.typed
job_orchestra-1.1.4.dist-info/METADATA
job_orchestra-1.1.4.dist-info/WHEEL
job_orchestra-1.1.4.dist-info/RECORD
