Metadata-Version: 2.4
Name: job-orchestra
Version: 1.1.4
Summary: The pipeline orchestration framework for data science workflows
Project-URL: Homepage, https://github.com/tomalf2/job-orchestra/
Project-URL: Source, https://github.com/tomalf2/job-orchestra/
Author: Tommaso Alfonsi
License-Expression: MIT
Keywords: orchestration,pipeline
Classifier: Intended Audience :: Developers
Classifier: License :: OSI Approved :: MIT License
Classifier: Natural Language :: English
Classifier: Operating System :: OS Independent
Classifier: Programming Language :: Python :: 3.11
Classifier: Programming Language :: Python :: 3.12
Classifier: Programming Language :: Python :: 3.13
Classifier: Topic :: Scientific/Engineering
Classifier: Topic :: Software Development
Requires-Python: >=3.11
Requires-Dist: cleverdict>=1.9.2
Requires-Dist: dagviz>=0.4.0
Requires-Dist: fastjsonschema>=2.21.1
Requires-Dist: flatdict>=4.0.1
Requires-Dist: numpy>=2.2.3
Requires-Dist: pandas>=2.2.3
Requires-Dist: pathvalidate>=3.2.3
Requires-Dist: pyarrow>=19.0.1
Requires-Dist: scikit-learn>=1.6.1
